[{"farmer_unique_id":"4761279","site_id":3147,"date":"2021-02-11","filename":"L141F03315C01S03147Rp13488.jpg","season":"SR2020","growth_stage":"F","damage":"WD","extent":10,"drought_probability":0.0038,"drought_extent":-1,"growth_sowing":4.2215e-06,"growth_vegetative":0.2661,"growth_flowering":0.1726,"growth_maturity":0.5613,"disturbance_none":0.8784,"disturbance_weeds":0.1135,"disturbance_drought":0.0075,"disturbance_nutrient_deficit":0.0006,"crop_name":"maize","spatial_location":"Mbeere-North"}]
