[{"farmer_unique_id":"3218278180","site_id":5644,"date":"2020-12-25","filename":"L321F01947C01S05644Rp07187.jpg","season":"SR2020","growth_stage":"V","damage":"WD","extent":20,"drought_probability":0.0011,"drought_extent":3,"growth_sowing":0.0001,"growth_vegetative":0.9971,"growth_flowering":0.0027,"growth_maturity":0.0001,"disturbance_none":0.0172,"disturbance_weeds":0.9824,"disturbance_drought":0.0004,"disturbance_nutrient_deficit":3.1993e-06,"crop_name":"maize","spatial_location":"Tigania-West"}]
