[{"farmer_unique_id":"3311479292","site_id":4022,"date":"2021-01-15","filename":"L331F04165C01S04022Rp10554.jpg","season":"SR2020","growth_stage":"F","damage":"G","extent":0,"drought_probability":0.0002,"drought_extent":1,"growth_sowing":9.2066e-07,"growth_vegetative":0.0005,"growth_flowering":0.9973,"growth_maturity":0.0022,"disturbance_none":0.9864,"disturbance_weeds":0.0133,"disturbance_drought":0.0003,"disturbance_nutrient_deficit":4.6549e-07,"crop_name":"maize","spatial_location":"Central-Imenti"}]
