[{"farmer_unique_id":"3317499997","site_id":4227,"date":"2020-12-05","filename":"L331F04179C01S04227Rp03063.jpg","season":"SR2020","growth_stage":"F","damage":"G","extent":0,"drought_probability":0.0663,"drought_extent":-0,"growth_sowing":0.0012,"growth_vegetative":0.3701,"growth_flowering":0.3705,"growth_maturity":0.2581,"disturbance_none":0.3234,"disturbance_weeds":0.6477,"disturbance_drought":0.0248,"disturbance_nutrient_deficit":0.004,"crop_name":"maize","spatial_location":"Central-Imenti"}]
