{
  "type": "Feature",
  "stac_version": "1.0.0",
  "id": "img_L371F02720C01S04963Rp14010",
  "properties": {
    "farmer_unique_id": "3995006",
    "site_id": 4963,
    "crop_name": "maize",
    "sowing_date": "2020-11-20",
    "expected_yield": 290,
    "season": "SR2020",
    "spatial_location": "Masinga",
    "spatial_unit": "gadm36",
    "datetime": "2021-02-15T15:58:39Z"
  },
  "geometry": {
    "type": "Polygon",
    "coordinates": [
      [
        [
          37.22516251,
          -1.12495291
        ],
        [
          37.22516251,
          -0.77446437
        ],
        [
          37.86812973,
          -0.77446437
        ],
        [
          37.86812973,
          -1.12495291
        ],
        [
          37.22516251,
          -1.12495291
        ]
      ]
    ]
  },
  "links": [
    {
      "rel": "root",
      "href": "https://raw.githubusercontent.com/khufkens/EotG_data/main/release_v1/EotG_images/Masinga/collection.json",
      "type": "application/json"
    },
    {
      "rel": "collection",
      "href": "https://raw.githubusercontent.com/khufkens/EotG_data/main/release_v1/EotG_images/Masinga/collection.json",
      "type": "application/json"
    },
    {
      "rel": "self",
      "href": "https://raw.githubusercontent.com/khufkens/EotG_data/main/release_v1/EotG_images/Masinga/img_L371F02720C01S04963Rp14010/img_L371F02720C01S04963Rp14010.json",
      "type": "application/json"
    },
    {
      "rel": "parent",
      "href": "https://raw.githubusercontent.com/khufkens/EotG_data/main/release_v1/EotG_images/Masinga/collection.json",
      "type": "application/json"
    }
  ],
  "assets": {
    "image": {
      "href": "https://raw.githubusercontent.com/khufkens/EotG_data/main/release_v1/images/L371F02720C01S04963Rp14010.jpg",
      "type": "image/jpeg",
      "title": "3 band RGB",
      "roles": [
        "data"
      ]
    },
    "label": {
      "href": "https://raw.githubusercontent.com/khufkens/EotG_data/main/release_v1/labels/L371F02720C01S04963Rp14010.json",
      "type": "application/json",
      "title": "ML labels",
      "roles": [
        "data"
      ]
    },
    "thumbnail": {
      "href": "https://raw.githubusercontent.com/khufkens/EotG_data/main/release_v1/thumbs/L371F02720C01S04963Rp14010.jpg",
      "type": "image/jpeg",
      "title": "thumbnail",
      "roles": [
        "thumbnail"
      ]
    },
    "sentinel": {
      "href": "https://raw.githubusercontent.com/khufkens/EotG_data/main/release_v1//ancillary_data/sentinel/3995006_4963_S2_R.zip",
      "type": "application/zip",
      "title": "Sentinel remote sensing data",
      "roles": [
        "data"
      ]
    },
    "ERA5": {
      "href": "https://raw.githubusercontent.com/khufkens/EotG_data/main/release_v1/ancillary_data/era5/3995006_4963_ERA5.zip",
      "type": "application/zip",
      "title": "ERA5 climate data",
      "roles": [
        "data"
      ]
    },
    "ARC": {
      "href": "https://raw.githubusercontent.com/khufkens/EotG_data/main/release_v1//ancillary_data/arc/3995006_4963_ARC.zip",
      "type": "application/zip",
      "title": "ARC precipitation estimates",
      "roles": [
        "data"
      ]
    },
    "TAMSAT": {
      "href": "https://raw.githubusercontent.com/khufkens/EotG_data/main/release_v1//ancillary_data/tamsat/3995006_4963_TAMSAT.zip",
      "type": "application/zip",
      "title": "TAMSAT precipitation estimates",
      "roles": [
        "data"
      ]
    }
  },
  "bbox": [
    37.22516251,
    -1.12495291,
    37.86812973,
    -0.77446437
  ],
  "stac_extensions": [],
  "collection": "Masinga"
}